ACME/ACME.py
ACME/ACME_anomaly_detection.py
ACME/ACME_function.py
ACME/ACME_plot.py
ACME/__init__.py
ACME/utils.py
ACME/visual_utils.py
statwolfACME-2.1.8.dist-info/METADATA
statwolfACME-2.1.8.dist-info/WHEEL
statwolfACME-2.1.8.dist-info/top_level.txt
statwolfACME-2.1.8.dist-info/RECORD
