Metadata-Version: 2.1
Name: statwolfACME
Version: 2.1.8
Summary: ACME - Accelerated Model Explainability
Home-page: https://github.com/dandolodavid/ACME
Author: Dandolo David
Author-email: dandolodavid@gmail.com
License: BSD 4-clause
Classifier: Development Status :: 5 - Production/Stable
Classifier: Intended Audience :: Science/Research
Classifier: Intended Audience :: Information Technology
Classifier: Intended Audience :: Legal Industry
Classifier: Intended Audience :: Manufacturing
Classifier: License :: OSI Approved :: BSD License
Classifier: Programming Language :: Python :: 3
Classifier: Programming Language :: Python :: 3.4
Classifier: Programming Language :: Python :: 3.5
Requires-Dist: numpy
Requires-Dist: pandas
Requires-Dist: plotly >4.0.0
